wapilot/__init__.py
wapilot/client.py
wapilot_sdk-1.0.0.dist-info/licenses/LICENSE
wapilot_sdk-1.0.0.dist-info/METADATA
wapilot_sdk-1.0.0.dist-info/WHEEL
wapilot_sdk-1.0.0.dist-info/top_level.txt
wapilot_sdk-1.0.0.dist-info/RECORD
