Metadata-Version: 2.4
Name: wapilot-sdk
Version: 1.0.0
Summary: Official Python SDK for WAPILOT.io - WhatsApp Business API Integration
Home-page: https://wapilot.io
Author: WAPILOT
Author-email: support@wapilot.io
Project-URL: Documentation, https://docs.wapilot.io
Project-URL: Source, https://github.com/wapilot/wapilot-python-sdk
Project-URL: Bug Tracker, https://github.com/wapilot/wapilot-python-sdk/issues
Classifier: Development Status :: 5 - Production/Stable
Classifier: Intended Audience :: Developers
Classifier: License :: OSI Approved :: MIT License
Classifier: Operating System :: OS Independent
Classifier: Programming Language :: Python :: 3
Classifier: Programming Language :: Python :: 3.7
Classifier: Programming Language :: Python :: 3.8
Classifier: Programming Language :: Python :: 3.9
Classifier: Programming Language :: Python :: 3.10
Classifier: Programming Language :: Python :: 3.11
Classifier: Topic :: Software Development :: Libraries :: Python Modules
Classifier: Topic :: Communications :: Chat
Requires-Python: >=3.7
License-File: LICENSE
Requires-Dist: requests>=2.25.0
Dynamic: author
Dynamic: author-email
Dynamic: classifier
Dynamic: description
Dynamic: description-content-type
Dynamic: home-page
Dynamic: license-file
Dynamic: project-url
Dynamic: requires-dist
Dynamic: requires-python
Dynamic: summary
